[
  {
    "id": "i-let-ai-build-my-portfolio",
    "title": "I let AI build my portfolio. Here is exactly what happened.",
    "date": "2026-03-31",
    "excerpt": "How one hour of AI execution followed a month of structured preparation — and why the prep was the entire point.",
    "tags": [
      "AI",
      "Portfolio",
      "Development",
      "Workflow"
    ],
    "cover": "assets/blogs/ai-portfolio/cover.png",
    "content": "# Why I decided to rebuild\n\nIt is the 6th semester of my engineering. Third year. The kind of point in college where you start feeling the weight of everything you have done so far, and also the pressure of everything you have not shown anyone yet.\n\nI run a technical club. I have projects, research papers, certificates, hackathon experiences, and things worth writing about. But when someone asked me for my portfolio, I would send them a link that felt embarrassing to open. Generic layout, hardcoded content, nothing that felt like me.\n\nSo I decided to rebuild it. Properly, this time. And I decided to see what would happen if I handed the build step to an AI agent.\n\n## The prep work nobody talks about\n\nBefore I opened any tool, I spent time doing something that sounds boring but turned out to be the most important part: organizing my own data.\n\nI went through every certificate image and stored them in labeled folders. I wrote out each project in a separate text file with screenshots organized alongside them. I documented my experience entries, tracked down research papers, and sorted hackathon records into their own directory. By the end I had a complete `Data Collection/` folder that was essentially a structured brain dump of three years of engineering.\n\nI also studied reference portfolios — not to copy them, but to understand what made each one feel the way it felt.\n\n- **opencode.ai** — confidence through restraint, terminal-native visual language\n- **tailwindcss.com** — typographic rhythm and purposeful whitespace\n- **abdulrehmanwaseem.me** — personality without loudness\n- **dhvanitmonpara.in** — minimal structure done with conviction\n\nI was building a visual vocabulary before I had anything to build with.\n\n## Writing the prompt\n\nI wrote a detailed prompt, then refined it specifically for the AI model I planned to use. The final version read closer to a technical specification than a request.\n\nIt included file paths to every data source, reference URLs for design direction, my old portfolio for context, and strict rules like zero hardcoded content and consistent theming. I also defined performance expectations, loading behavior, commit practices, and how the system should maintain state across steps.\n\nThe prompt took longer to write than the build took to run. That ratio turned out to be the entire lesson.\n\n## What the agent actually did\n\nI gave the prompt to an AI coding agent through a development environment.\n\nThe agent started by reading everything. It fetched my LinkedIn profile, visited my old portfolio, parsed my resume, and analyzed every project folder along with associated assets. It even extracted accurate metadata from certificate images, including dates, issuers, and titles.\n\nFrom there it moved systematically through the build.\n\n### 1. Data pipeline first\n\nBefore building the interface, it structured all content into clean, consistent JSON files. Personal information, projects, skills, research papers, activities, and certificates were all organized with unique identifiers and clear relationships.\n\n### 2. Asset organization\n\nIt processed and optimized assets, converting files into web-friendly formats and organizing everything into a clean directory structure.\n\n### 3. Design system setup\n\nIt created a consistent design system using a centralized configuration, ensuring that colors, spacing, and typography remained uniform across the entire portfolio.\n\n### 4. Sections built in order\n\nThe portfolio was built section by section: Hero, About, Experience, Skills, Projects, Research, Contact, followed by blog and resource pages. Each section dynamically loaded its content from structured data instead of relying on hardcoded values.\n\n### 5. Performance considerations\n\nFor content-heavy sections, it implemented lazy loading and loading placeholders so the site remained responsive while data and images were fetched.\n\n### 6. Version control discipline\n\nIt maintained clean version control practices, committing changes after each major step with clear, structured messages. The repository history ended up reading like a well-organized changelog.\n\n**Total time from first command to final push: one hour.**\n\n## What I actually learned\n\nThe agent did not do the work. I did the work. The agent just executed faster than I could.\n\nEvery decision that made the output good was made before I opened the tool. The folder structure, the data schema, the design references, and all the constraints came from deliberate thinking.\n\nIf I had written a vague prompt, I would have gotten a generic portfolio. The specificity of the input was the entire reason the output was not generic.\n\nAI made execution instant. It did not make thinking optional.\n\n## What this changes about how I work\n\nThis experience changed how I think about skill. The advantage is no longer just speed of execution. It is clarity of thought, precision in structuring problems, and the ability to communicate intent without ambiguity.\n\nThat has always mattered. AI just makes the difference more visible. The gap between clear thinking and unclear thinking is no longer hours of effort — it is the difference between something generic and something genuinely personal.\n\n---\n\nIf you are thinking about rebuilding your portfolio: spend the time before using any AI tool. Organize your data. Study designs you respect. Define exactly what you want. Then let the agent handle execution.\n\nThe one-hour build only worked because of the month that came before it."
  }
]